dtwParallel-0.9.41-py3.11-nspkg.pth
dtwParallel/_version.py
dtwParallel/configuration.ini
dtwParallel/dtwParallel.py
dtwParallel/dtw_functions.py
dtwParallel/error_control.py
dtwParallel/utils.py
dtwParallel/utils_visualizations.py
dtwparallel-0.9.41.dist-info/AUTHORS
dtwparallel-0.9.41.dist-info/LICENSE
dtwparallel-0.9.41.dist-info/METADATA
dtwparallel-0.9.41.dist-info/WHEEL
dtwparallel-0.9.41.dist-info/entry_points.txt
dtwparallel-0.9.41.dist-info/namespace_packages.txt
dtwparallel-0.9.41.dist-info/top_level.txt
dtwparallel-0.9.41.dist-info/RECORD
