Metadata-Version: 2.2
Name: dtwParallel
Version: 0.9.41
Summary: Python implementation of Dynamic Time Warping (DTW), which allows computing the dtw distance between one-dimensional and multidimensional time series, with the possibility of visualisation (one-dimensional case) and parallelisation (multidimensional case).
Home-page: https://github.com/oscarescuderoarnanz/dtwParallel
Author: oscarescuderoarnanz
Author-email: Óscar <escuderoarnanzoscar@gmail.com>
License: BSD 2-Clause License
Project-URL: Homepage, https://github.com/oscarescuderoarnanz/dtwParallel
Keywords: dtw,parallel,CPU
Classifier: Intended Audience :: Science/Research
Classifier: Topic :: Scientific/Engineering
Classifier: License :: OSI Approved :: BSD License
Classifier: Programming Language :: Python :: 3
Requires-Python: >=3.6.1
License-File: LICENSE
License-File: AUTHORS
Requires-Dist: numpy
Requires-Dist: pandas
Requires-Dist: matplotlib
Requires-Dist: seaborn
Requires-Dist: gower
Requires-Dist: setuptools
Requires-Dist: scipy
Requires-Dist: joblib
Requires-Dist: numba
Dynamic: author
Dynamic: home-page
